[
    {
        "Title": "Go to Azure portal. Browse Web app deployed in App Service."
    },
    {
        "Title": "Go to Configuration, Application settings."
    },
    {
        "Title": "To see details of errors on your page set production envirenment to development mode.",
        "Codes": [
            {
                "Nr": 1,
                "CodeFormat": "ASPNETCORE_ENVIRONMENT",
                "CodeParams": [
                    {
                        "Name": "",
                        "Desc": "Key/Name",
                        "CssClass": "mark-name"
                    }
                ]
            },
            {
                "Nr": 2,
                "CodeFormat": "Development",
                "CodeParams": [
                    {
                        "Name": "",
                        "Desc": "Value",
                        "CssClass": "mark-name"
                    }
                ]
            }
        ]
    },
    {
        "Title": "Instead of using ConnectionString in appsetings.json.<br>I use builder class.<br>For it to work add below key/value pairs.",
        "Codes": [
            {
                "Nr": 3,
                "CodeFormat": "Server",
                "CodeParams": [
                    {
                        "Name": "",
                        "Desc": "Key/Name required for connection to db",
                        "CssClass": "mark-name"
                    }
                ]
            },
            {
                "Nr": 4,
                "CodeFormat": "atari-monk-sql-server1.database.windows.net",
                "CodeParams": [
                    {
                        "Name": "",
                        "Desc": "example Value",
                        "CssClass": "mark-name"
                    }
                ]
            },
            {
                "Nr": 5,
                "CodeFormat": "DbPort",
                "CodeParams": [
                    {
                        "Name": "",
                        "Desc": "Key/Name required for connection to db",
                        "CssClass": "mark-name"
                    }
                ]
            },
            {
                "Nr": 6,
                "CodeFormat": "1433",
                "CodeParams": [
                    {
                        "Name": "",
                        "Desc": "example Value",
                        "CssClass": "mark-name"
                    }
                ]
            },
            {
                "Nr": 7,
                "CodeFormat": "DbUser",
                "CodeParams": [
                    {
                        "Name": "",
                        "Desc": "Key/Name required for connection to db",
                        "CssClass": "mark-name"
                    }
                ]
            },
            {
                "Nr": 8,
                "CodeFormat": "atari-monk",
                "CodeParams": [
                    {
                        "Name": "",
                        "Desc": "example Value",
                        "CssClass": "mark-name"
                    }
                ]
            },
            {
                "Nr": 9,
                "CodeFormat": "DbPassword",
                "CodeParams": [
                    {
                        "Name": "",
                        "Desc": "Key/Name required for connection to db",
                        "CssClass": "mark-name"
                    }
                ]
            },
            {
                "Nr": 10,
                "CodeFormat": "password",
                "CodeParams": [
                    {
                        "Name": "",
                        "Desc": "example Value",
                        "CssClass": "mark-name"
                    }
                ]
            },
            {
                "Nr": 11,
                "CodeFormat": "Database",
                "CodeParams": [
                    {
                        "Name": "",
                        "Desc": "Key/Name required for connection to db",
                        "CssClass": "mark-name"
                    }
                ]
            },
            {
                "Nr": 12,
                "CodeFormat": "todo-db",
                "CodeParams": [
                    {
                        "Name": "",
                        "Desc": "example Value",
                        "CssClass": "mark-name"
                    }
                ]
            }
        ]
    }
]